fob/__init__.py
fob/base.py
fob/cli.py
fob/ingredient.py
fob/serialize.py
fob/store.py
fob/types.py
fob-0.0.5.dist-info/LICENSE
fob-0.0.5.dist-info/METADATA
fob-0.0.5.dist-info/WHEEL
fob-0.0.5.dist-info/top_level.txt
fob-0.0.5.dist-info/RECORD
