Metadata-Version: 2.1
Name: fob
Version: 0.0.5
Summary: a library for building configurable, repeatable experiments
Home-page: https://github.com/andrewyates/fob
Author: Andrew Yates
Author-email: first-then-last@mail-service-by-g.com
Classifier: Programming Language :: Python :: 3
Classifier: Operating System :: OS Independent
Requires-Python: >=3.9
License-File: LICENSE
Requires-Dist: colorlog
Requires-Dist: numpy
